LICENSE
MANIFEST.in
README.md
setup.py
insteon/__init__.py
insteon/api.py
insteon/authorization.py
insteon/categories.yml
insteon/const.py
insteon/insteon.py
insteon/resources.py
insteon_hub.egg-info/PKG-INFO
insteon_hub.egg-info/SOURCES.txt
insteon_hub.egg-info/dependency_links.txt
insteon_hub.egg-info/requires.txt
insteon_hub.egg-info/top_level.txt