Metadata-Version: 1.1
Name: insteon-hub
Version: 0.4.5
Summary: A python package that interacts with the Insteon Hub Cloud API
Home-page: https://github.com/FreekingDean/insteon-hub
Author: Dean Galvin
Author-email: deangalvin3@gmail.com
License: MIT
Keywords: insteon,hub,cloud
Platform: UNKNOWN
Classifier: Intended Audience :: Developers
Classifier: Development Status :: 3 - Alpha
Classifier: Topic :: Home Automation
Classifier: Operating System :: OS Independent
Classifier: Programming Language :: Python :: 3.4
Classifier: License :: OSI Approved :: MIT License
